tracticketrpc/__init__.py
tracticketrpc/rpctickethandler.py
trac_ticketrpc-0.9.3.dist-info/METADATA
trac_ticketrpc-0.9.3.dist-info/WHEEL
trac_ticketrpc-0.9.3.dist-info/entry_points.txt
trac_ticketrpc-0.9.3.dist-info/licenses/LICENSE
trac_ticketrpc-0.9.3.dist-info/RECORD
