Metadata-Version: 2.4
Name: trac-ticketrpc
Version: 0.9.3
Summary: Trac JSON RPC plugin for ticket management
Project-URL: Homepage, https://github.com/FrankSommer-64/trac-ticketrpc
Project-URL: Issues, https://github.com/FrankSommer-64/trac-ticketrpcissues
Author-email: Frank Sommer <Frank.Sommer@sherpa-software.de>
Maintainer-email: Frank Sommer <Frank.Sommer@sherpa-software.de>
License-File: LICENSE
Classifier: Development Status :: 4 - Beta
Classifier: Intended Audience :: System Administrators
Classifier: License :: OSI Approved :: MIT License
Classifier: Operating System :: OS Independent
Classifier: Programming Language :: Python :: 3
Classifier: Topic :: Software Development :: Bug Tracking
Requires-Python: >=3.7
Requires-Dist: trac>=1.6
